signal_design/__init__.py
signal_design/axis.py
signal_design/core.py
signal_design/default_functions.py
signal_design/exc.py
signal_design/help_types.py
signal_design/relation.py
signal_design/signal.py
signal_design/spectrum.py
signal_design-0.4.0.dist-info/LICENSE
signal_design-0.4.0.dist-info/WHEEL
signal_design-0.4.0.dist-info/METADATA
signal_design-0.4.0.dist-info/RECORD
