Metadata-Version: 2.1
Name: signal-design
Version: 0.4.0
Summary: The project for creation and analysis signals.
Home-page: https://github.com/Omnivanitate/signal-design
License: MIT
Author: Omnivanitate
Author-email: serebraykov.vs@gmail.com
Requires-Python: >=3.6,<4.0
Classifier: License :: OSI Approved :: MIT License
Classifier: Programming Language :: Python :: 3
Classifier: Programming Language :: Python :: 3.6
Classifier: Programming Language :: Python :: 3.7
Classifier: Programming Language :: Python :: 3.8
Classifier: Programming Language :: Python :: 3.9
Classifier: Programming Language :: Python :: 3.10
Classifier: Programming Language :: Python :: 3.11
Requires-Dist: numpy (<=1.19); python_version >= "3.6" and python_version < "3.8"
Requires-Dist: numpy (>1.19); python_version >= "3.8"
Requires-Dist: packaging (>=21.3)
Requires-Dist: scipy (>=1.2,<1.8); python_version >= "3.6" and python_version < "3.8"
Requires-Dist: scipy (>=1.8); python_version >= "3.8"
Requires-Dist: typing_extensions (>=4.0)
Project-URL: Documentation, https://signal-design.readthedocs.io
Project-URL: Repository, https://github.com/Omnivanitate/signal-design
